xsensing_client/__init__.py
xsensing_client/version.py
xsensing_client/src/__init__.py
xsensing_client/src/uaic.py
xsensing_client/src/socket/__init__.py
xsensing_client/src/socket/socket_example_client.py
xsensing_client/src/socket/uaic_socket.py
xsensing_client-0.1.0.dist-info/METADATA
xsensing_client-0.1.0.dist-info/WHEEL
xsensing_client-0.1.0.dist-info/top_level.txt
xsensing_client-0.1.0.dist-info/RECORD
