Metadata-Version: 2.1
Name: xsensing-client
Version: 0.1.0
Summary: XSensing Unified AI Interface Client, UAIC
Home-page: https://github.com/zhangzhengde0225/xsensing_client
Author: Zhengde Zhang, XXX
Author-email: drivener@163.com
License: MIT
Platform: UNKNOWN
Classifier: License :: OSI Approved :: MIT License
Classifier: Programming Language :: Python
Classifier: Programming Language :: Python :: 3
Classifier: Programming Language :: Python :: 3.6
Classifier: Programming Language :: Python :: Implementation :: CPython
Classifier: Programming Language :: Python :: Implementation :: PyPy
Requires-Python: >=3.6.0
